stecker/__init__.py
stecker-1.0.0b1.dist-info/LICENSES/Apache-2.0.txt
stecker-1.0.0b1.dist-info/METADATA
stecker-1.0.0b1.dist-info/WHEEL
stecker-1.0.0b1.dist-info/RECORD
