Metadata-Version: 2.1
Name: stecker
Version: 1.0.0b1
Summary: Plugin framework using subclasses and entrypoints
Home-page: https://edugit.org/AlekSIS/libs/stecker
License: Apache-2.0
Author: Jonathan Weth
Author-email: dev@jonathanweth.de
Requires-Python: >=3.11,<4.0
Classifier: License :: OSI Approved :: Apache Software License
Classifier: Programming Language :: Python :: 3
Classifier: Programming Language :: Python :: 3.11
Project-URL: Repository, https://edugit.org/AlekSIS/libs/stecker
